bistory.py
bistory-1.1.0.dist-info/METADATA
bistory-1.1.0.dist-info/RECORD
bistory-1.1.0.dist-info/WHEEL
bistory-1.1.0.dist-info/entry_points.txt
bistory-1.1.0.dist-info/top_level.txt
