Metadata-Version: 2.1
Name: bistory
Version: 1.1.0
Summary: bash history search tool
Home-page: https://github.com/sivel/bistory
Author: Matt Martz
Author-email: matt@sivel.net
License: Apache License, Version 2.0
Keywords: bash history
Platform: UNKNOWN
Classifier: Development Status :: 5 - Production/Stable
Classifier: Programming Language :: Python
Classifier: Environment :: Console
Classifier: License :: OSI Approved :: Apache Software License
Classifier: Operating System :: OS Independent
Classifier: Programming Language :: Python :: 3
Classifier: Programming Language :: Python :: 3.5
Classifier: Programming Language :: Python :: 3.6
Classifier: Programming Language :: Python :: 3.7
Requires-Dist: prompt-toolkit (==2.0.3)
